MANIFEST.in
setup.cfg
setup.py
doc/changes.rst
doc/conf.py
doc/index.rst
doc/installation.rst
doc/reference.rst
doc/usage.rst
doc/vcs-integration.rst
versiontools/__init__.py
versiontools/bzr_support.py
versiontools/git_support.py
versiontools/tests.py
versiontools.egg-info/PKG-INFO
versiontools.egg-info/SOURCES.txt
versiontools.egg-info/dependency_links.txt
versiontools.egg-info/entry_points.txt
versiontools.egg-info/top_level.txt
versiontools.egg-info/zip-safe